autotwin_pmswsgi.py
autotwin_pmswsgi-1.0.4.dist-info/METADATA
autotwin_pmswsgi-1.0.4.dist-info/WHEEL
autotwin_pmswsgi-1.0.4.dist-info/licenses/LICENSE
autotwin_pmswsgi-1.0.4.dist-info/RECORD
