Metadata-Version: 2.4
Name: autotwin_pmswsgi
Version: 1.0.4
Summary: Process Mining Service WSGI for Auto-Twin
License: BSD-3-Clause
License-File: LICENSE
Keywords: auto-twin,system discovery,soc estimation,restful service
Author: Lulai Zhu
Author-email: lulai.zhu@gmail.com
Requires-Python: >=3.10,<4.0
Classifier: Development Status :: 1 - Planning
Classifier: Intended Audience :: Manufacturing
Classifier: License :: OSI Approved :: BSD License
Classifier: Operating System :: OS Independent
Classifier: Programming Language :: Python :: 3
Classifier: Programming Language :: Python :: 3.10
Classifier: Programming Language :: Python :: 3.11
Classifier: Programming Language :: Python :: 3.12
Classifier: Programming Language :: Python :: 3.13
Classifier: Programming Language :: Python :: 3.14
Classifier: Programming Language :: Python :: 3 :: Only
Requires-Dist: Flask (>=3.0.2,<4.0.0)
Requires-Dist: Paste (>=3.7.1,<4.0.0)
Requires-Dist: autotwin_autlib (>=0.1.4,<0.2.0)
Requires-Dist: autotwin_bselib (>=0.1.2,<0.2.0)
Requires-Dist: autotwin_gmglib (>=0.1.17,<0.2.0)
Requires-Dist: autotwin_pnglib (>=0.1.2,<0.2.0)
Requires-Dist: waitress (>=3.0.0,<4.0.0)
Project-URL: Homepage, https://github.com/AutotwinEU/proc-mining-serv
